xchainpy2_ethereum/__init__.py
xchainpy2_ethereum/const.py
xchainpy2_ethereum/decode_logs.py
xchainpy2_ethereum/eth_client.py
xchainpy2_ethereum/gas.py
xchainpy2_ethereum/token_info.py
xchainpy2_ethereum/utils.py
xchainpy2_ethereum/data/eth_mainnet_latest.json
xchainpy2_ethereum/data/abi/erc20.json
xchainpy2_ethereum/data/abi/router.json
xchainpy2_ethereum/extra/__init__.py
xchainpy2_ethereum/extra/base.py
xchainpy2_ethereum/extra/etherscan.py
xchainpy2_ethereum/extra/moralis_provider.py
xchainpy2_ethereum/tests/test_addr.py
xchainpy2_ethereum-0.0.19.dist-info/LICENSE
xchainpy2_ethereum-0.0.19.dist-info/METADATA
xchainpy2_ethereum-0.0.19.dist-info/WHEEL
xchainpy2_ethereum-0.0.19.dist-info/top_level.txt
xchainpy2_ethereum-0.0.19.dist-info/RECORD
